DBHelper/__init__.py
DBHelper/dbddl.py
DBHelper/sqlite_db_operations.py
microservices/__init__.py
microservices/tasks.py
inn_digialert_Mylist-0.0.1.dist-info/METADATA
inn_digialert_Mylist-0.0.1.dist-info/WHEEL
inn_digialert_Mylist-0.0.1.dist-info/top_level.txt
inn_digialert_Mylist-0.0.1.dist-info/RECORD
