Metadata-Version: 2.1
Name: inn-digialert-Mylist
Version: 0.0.1
Summary: MyList api built in Flask and sqlite
Home-page: https://bitbucket.org/Radio_fixed/sqliteforkarate/src/master/
Author: SimpleAppDesigner
Author-email: Sandeep1dimri@gmail.com
License: UNKNOWN
Platform: UNKNOWN
Classifier: Programming Language :: Python :: 3
Classifier: License :: OSI Approved :: MIT License
Classifier: Operating System :: OS Independent
Requires-Python: >=3.6
Requires-Dist: click (==7.1.2)
Requires-Dist: Flask (==1.1.2)
Requires-Dist: itsdangerous (==1.1.0)
Requires-Dist: Jinja2 (==2.11.3)
Requires-Dist: MarkupSafe (==1.1.1)
Requires-Dist: Werkzeug (==1.0.1)
